{"name":"build-javascript","namedChunkGroups":{"app":{"name":"app","assets":[{"name":"webpack-runtime-05bf28c7957122704e9a.js","size":3817},{"name":"framework-ac76b7381dcb92e64e9c.js","size":141411},{"name":"app-68ad7d9b8bcac124c4b8.js","size":114175}],"filteredAssets":0,"assetsSize":259403,"filteredAuxiliaryAssets":3,"auxiliaryAssetsSize":773905},"component---src-pages-404-js":{"name":"component---src-pages-404-js","assets":[{"name":"component---src-pages-404-js-cf3db80dd1e57c26ad54.js","size":796}],"filteredAssets":0,"assetsSize":796,"filteredAuxiliaryAssets":1,"auxiliaryAssetsSize":1750},"component---src-pages-index-js":{"name":"component---src-pages-index-js","assets":[{"name":"framework-ac76b7381dcb92e64e9c.js","size":141411},{"name":"b637e9a5-2edd2e97587d0fd698dc.js","size":90592},{"name":"component---src-pages-index-js-ebee1e8b01bd1aa13393.js","size":80706}],"filteredAssets":0,"assetsSize":312709,"filteredAuxiliaryAssets":5,"auxiliaryAssetsSize":1247164}},"assetsByChunkName":{"app":["webpack-runtime-05bf28c7957122704e9a.js","framework-ac76b7381dcb92e64e9c.js","app-68ad7d9b8bcac124c4b8.js"],"component---src-pages-404-js":["component---src-pages-404-js-cf3db80dd1e57c26ad54.js"],"component---src-pages-index-js":["framework-ac76b7381dcb92e64e9c.js","b637e9a5-2edd2e97587d0fd698dc.js","component---src-pages-index-js-ebee1e8b01bd1aa13393.js"]},"childAssetsByChunkName":{}}